PatelHet_STT/__init__.py
PatelHet_STT-0.1.dist-info/METADATA
PatelHet_STT-0.1.dist-info/WHEEL
PatelHet_STT-0.1.dist-info/top_level.txt
PatelHet_STT-0.1.dist-info/RECORD
