Metadata-Version: 2.1
Name: PatelHet_STT
Version: 0.1
Summary: this is speech to text packeg created by patel het
Author: Patel Het
Author-email: patelhet8265@gmail.com
